wait_for_service/__init__.py
wait_for_service/checks/__init__.py
wait_for_service/checks/amqp.py
wait_for_service/checks/http.py
wait_for_service/checks/https.py
wait_for_service/checks/kafka.py
wait_for_service/checks/memcached.py
wait_for_service/checks/mongodb.py
wait_for_service/checks/mysql.py
wait_for_service/checks/postgres.py
wait_for_service/checks/redis.py
wait_for_service/checks/tcp.py
wait_for_service/checks/unix.py
wait_for_service/wait_for_service.py
wait_for_service-1.2.1.dist-info/LICENSE
wait_for_service-1.2.1.dist-info/METADATA
wait_for_service-1.2.1.dist-info/WHEEL
wait_for_service-1.2.1.dist-info/entry_points.txt
wait_for_service-1.2.1.dist-info/RECORD
