Metadata-Version: 2.1
Name: wait-for-service
Version: 1.2.1
Summary: 
License: MIT
Author: Ryan Faircloth
Author-email: ryan@dss-i.com
Requires-Python: >=3.11,<4.0
Classifier: License :: OSI Approved :: MIT License
Classifier: Programming Language :: Python :: 3
Classifier: Programming Language :: Python :: 3.11
Provides-Extra: kafka
Provides-Extra: memcached
Provides-Extra: mongodb
Provides-Extra: mysql
Provides-Extra: postgres
Provides-Extra: psycopg
Provides-Extra: rabbitmq
Provides-Extra: redis
Provides-Extra: websockets
Requires-Dist: furl (>=2.1.3,<3.0.0)
Requires-Dist: kafka-python (>=2.0.2,<3.0.0) ; extra == "kafka"
Requires-Dist: mysql-connector-python (>=8.1.0,<9.0.0) ; extra == "mysql"
Requires-Dist: pika (>=1.3.2,<2.0.0) ; extra == "rabbitmq"
Requires-Dist: psycopg2-binary (>=2.9.9,<3.0.0) ; extra == "postgres"
Requires-Dist: psycopg[binary] (>=3.1.12,<4.0.0) ; extra == "psycopg"
Requires-Dist: pymongo (>=4.5.0,<5.0.0) ; extra == "mongodb"
Requires-Dist: python3-memcached (>=1.51,<2.0) ; extra == "memcached"
Requires-Dist: redis (>=5.0.1,<6.0.0) ; extra == "redis"
Requires-Dist: requests (>=2.31.0,<3.0.0)
Requires-Dist: websocket-server (>=0.6.4,<0.7.0) ; extra == "websockets"
